container_patcher/__init__.py
container_patcher/api.py
container_patcher/cli.py
container_patcher/container_patcher.py
container_patcher-0.1.3.dist-info/AUTHORS.rst
container_patcher-0.1.3.dist-info/LICENSE
container_patcher-0.1.3.dist-info/METADATA
container_patcher-0.1.3.dist-info/WHEEL
container_patcher-0.1.3.dist-info/entry_points.txt
container_patcher-0.1.3.dist-info/top_level.txt
container_patcher-0.1.3.dist-info/RECORD
