Metadata-Version: 2.1
Name: container-patcher
Version: 0.1.3
Summary: A tool to automatically fix vulnerable container packages.
Home-page: https://github.com/yamagn/container_patcher
Author: Kenya Yamamoto
Author-email: syankenpon@gmail.com
License: MIT license
Keywords: container_patcher
Platform: UNKNOWN
Classifier: Development Status :: 2 - Pre-Alpha
Classifier: Intended Audience :: Developers
Classifier: License :: OSI Approved :: MIT License
Classifier: Natural Language :: English
Classifier: Programming Language :: Python :: 3
Classifier: Programming Language :: Python :: 3.5
Classifier: Programming Language :: Python :: 3.6
Classifier: Programming Language :: Python :: 3.7
Classifier: Programming Language :: Python :: 3.8
Requires-Python: >=3.5
Requires-Dist: Click (>=7.0)
